[
  {
    "id": "m-001",
    "nameZh": "李老师",
    "nameEn": "Professor Li",
    "roleZh": "导师",
    "roleEn": "Supervisor",
    "group": "teacher",
    "avatar": "li.png"
  },
  {
    "id": "m-002",
    "nameZh": "张三",
    "nameEn": "Zhang San",
    "roleZh": "博士研究生",
    "roleEn": "PhD Student",
    "group": "phd",
    "avatar": "zhangsan.png"
  },
  {
    "id": "m-1761979531524",
    "nameZh": "1",
    "nameEn": "1",
    "roleZh": "1",
    "roleEn": "1",
    "group": "phd",
    "avatar": ""
  },
  {
    "id": "m-1761979536019",
    "nameZh": "2",
    "nameEn": "2",
    "roleZh": "2",
    "roleEn": "2",
    "group": "phd",
    "avatar": ""
  }
]